<Properties StartupConfiguration="{C09862AE-A81B-4F43-8DAC-671FCEE99B6C}|Default">
  <MultiItemStartupConfigurations />
  <MonoDevelop.Ide.Workspace ActiveConfiguration="Debug" />
  <MonoDevelop.Ide.ItemProperties.CProm__Lab2 PreferredExecutionTarget="MonoDevelop.Default" />
  <MonoDevelop.Ide.Workbench ActiveDocument="CProm_Lab2.cs">
    <Files>
      <File FileName="SimpleMath.cs" Line="15" Column="34" />
    </Files>
    <Pads>
      <Pad Id="ProjectPad">
        <State name="__root__">
          <Node name="CProm_Lab2" expanded="True">
            <Node name="CProm_Lab2">
              <Node name="CProm_Lab2.cs" selected="True" />
            </Node>
          </Node>
        </State>
      </Pad>
    </Pads>
  </MonoDevelop.Ide.Workbench>
  <MonoDevelop.Ide.DebuggingService.Breakpoints>
    <BreakpointStore />
  </MonoDevelop.Ide.DebuggingService.Breakpoints>
  <MonoDevelop.Ide.DebuggingService.PinnedWatches />
</Properties>